jb4jupyter/__init__.py
jb4jupyter/brint.py
jb4jupyter/plotpretty.py
jb4jupyter-0.18.dist-info/METADATA
jb4jupyter-0.18.dist-info/WHEEL
jb4jupyter-0.18.dist-info/top_level.txt
jb4jupyter-0.18.dist-info/RECORD
