Metadata-Version: 2.1
Name: jb4jupyter
Version: 0.18
Summary: jupyter bettifier by @jb4earth
Home-page: http://gitlab.com/jb4earth/jb4jupyter
Author: @jb4earth
Author-email: jb4earth@gmail.com
License: GPL
Platform: UNKNOWN
